pgs3/__about__.py
pgs3/__init__.py
pgs3/cli.py
pgs3-0.0.4.dist-info/METADATA
pgs3-0.0.4.dist-info/WHEEL
pgs3-0.0.4.dist-info/entry_points.txt
pgs3-0.0.4.dist-info/licenses/LICENSE.txt
pgs3-0.0.4.dist-info/RECORD
