Metadata-Version: 2.3
Name: pgs3
Version: 0.0.4
Summary: A command-line tool for backing up and restoring PostgreSQL databases to/from S3-compatible storage.
Project-URL: Documentation, https://github.com/Hao Wu/pgs3#readme
Project-URL: Issues, https://github.com/Hao Wu/pgs3/issues
Project-URL: Source, https://github.com/Hao Wu/pgs3
Author-email: Hao Wu <haowu@dataset.sh>
License-Expression: MIT
License-File: LICENSE.txt
Classifier: Development Status :: 4 - Beta
Classifier: Programming Language :: Python
Classifier: Programming Language :: Python :: 3.8
Classifier: Programming Language :: Python :: 3.9
Classifier: Programming Language :: Python :: 3.10
Classifier: Programming Language :: Python :: 3.11
Classifier: Programming Language :: Python :: 3.12
Classifier: Programming Language :: Python :: Implementation :: CPython
Classifier: Programming Language :: Python :: Implementation :: PyPy
Requires-Python: >=3.9
Requires-Dist: boto3~=1.20.0
Requires-Dist: click~=8.1.3
Requires-Dist: pydantic~=2.0.3
